schedule_tweet/__init__.py
schedule_tweet/browser.py
schedule_tweet/page_objects/__init__.py
schedule_tweet/page_objects/app_page.py
schedule_tweet/page_objects/landing_page.py
schedule_tweet/page_objects/login_page.py
schedule_tweet-1.0.0.dist-info/DESCRIPTION.rst
schedule_tweet-1.0.0.dist-info/METADATA
schedule_tweet-1.0.0.dist-info/RECORD
schedule_tweet-1.0.0.dist-info/WHEEL
schedule_tweet-1.0.0.dist-info/metadata.json
schedule_tweet-1.0.0.dist-info/top_level.txt
