Metadata-Version: 2.0
Name: schedule-tweet
Version: 1.0.0
Summary: Schedules tweets using TweetDeck
Home-page: https://github.com/honzajavorek/schedule-tweet
Author: Honza Javorek
Author-email: mail@honzajavorek.cz
License: MIT
Keywords: tweet tweets twitter tweetdeck scheduling scheduler
Platform: UNKNOWN
Classifier: Development Status :: 3 - Alpha
Classifier: Intended Audience :: Developers
Classifier: License :: OSI Approved :: MIT License
Classifier: Programming Language :: Python :: 3
Classifier: Programming Language :: Python :: 3.6
Classifier: Programming Language :: Python :: 3.7
Requires-Dist: selenium (~=3.5.0)
Provides-Extra: release
Requires-Dist: python-semantic-release (~=3.10.2); extra == 'release'
Provides-Extra: tests
Requires-Dist: requests (~=2.18.4); extra == 'tests'
Requires-Dist: lxml (~=4.1.1); extra == 'tests'
Requires-Dist: cssselect (~=1.0.1); extra == 'tests'
Requires-Dist: pytz (>=2017.3); extra == 'tests'
